sentinel/__init__.py
sentinel/files.py
sentinel/path.py
sentinel/puts.py
sentinel/sentinel.py
sentinel/snap.py
sentinel/utils.py
PoseidonSentinel-0.1.2.dist-info/LICENSE
PoseidonSentinel-0.1.2.dist-info/METADATA
PoseidonSentinel-0.1.2.dist-info/WHEEL
PoseidonSentinel-0.1.2.dist-info/top_level.txt
PoseidonSentinel-0.1.2.dist-info/RECORD
