Metadata-Version: 2.1
Name: PoseidonSentinel
Version: 0.1.2
Summary: A network based file tracking system
Home-page: UNKNOWN
Author: Johnny Whitworth
Author-email: jwhitworth@arizonapipeline.com
License: UNKNOWN
Project-URL: Sentinel, https://github.com/Poseidon-Dev/sentinel
Platform: UNKNOWN
Classifier: Development Status :: 4 - Beta
Classifier: Intended Audience :: Other Audience
Classifier: License :: OSI Approved :: MIT License
Classifier: Natural Language :: English
Classifier: Programming Language :: Python :: 3.9
Classifier: Operating System :: Microsoft :: Windows
Requires-Python: >=3.6
License-File: LICENSE
